dnaweaver/__init__.py
dnaweaver/tools.py
dnaweaver/version.py
dnaweaver/AssemblyPlanReport/AssemblyPlanReport.py
dnaweaver/AssemblyPlanReport/ObjectDict.py
dnaweaver/AssemblyPlanReport/__init__.py
dnaweaver/AssemblyPlanReport/config.py
dnaweaver/AssemblyPlanReport/assets/fonts/OpenSans-Light.ttf
dnaweaver/AssemblyPlanReport/assets/fonts/fontawesome-webfont.ttf
dnaweaver/AssemblyPlanReport/assets/templates/FOLDER_README.txt
dnaweaver/AssemblyPlanReport/assets/templates/report_template.html
dnaweaver/AssemblyPlanReport/assets/templates/static/css/dnaweaver_report.css
dnaweaver/AssemblyPlanReport/assets/templates/static/images/assembly_blocks.svg
dnaweaver/AssemblyPlanReport/assets/templates/static/images/dna_weaver_logo.svg
dnaweaver/AssemblyPlanReport/assets/templates/static/images/egf_logo.png
dnaweaver/AssemblyPlanReport/assets/templates/static/images/supply_chain.svg
dnaweaver/AssemblyPlanReport/mixins/FolderReportMixin.py
dnaweaver/AssemblyPlanReport/mixins/GenbankExportMixin.py
dnaweaver/AssemblyPlanReport/mixins/PdfReportMixin.py
dnaweaver/AssemblyPlanReport/mixins/__init__.py
dnaweaver/AssemblyPlanReport/mixins/PlotsMixin/AssemblyBlocksMixin.py
dnaweaver/AssemblyPlanReport/mixins/PlotsMixin/AssemblyGraphMixin.py
dnaweaver/AssemblyPlanReport/mixins/PlotsMixin/ColorsMixin.py
dnaweaver/AssemblyPlanReport/mixins/PlotsMixin/PlotsMixin.py
dnaweaver/AssemblyPlanReport/mixins/PlotsMixin/TimelineMixin.py
dnaweaver/AssemblyPlanReport/mixins/PlotsMixin/__init__.py
dnaweaver/AssemblyPlanReport/mixins/PlotsMixin/give_quotes_html_locations.py
dnaweaver/AssemblyPlanReport/mixins/PlotsMixin/matplotlib_export.py
dnaweaver/AssemblyPlanReport/mixins/PlotsMixin/plot_supply_network.py
dnaweaver/AssemblyPlanReport/mixins/PlotsMixin/plot_tree_graph.py
dnaweaver/DnaAssemblyMethod/BluntEndAssemblyMethod.py
dnaweaver/DnaAssemblyMethod/DnaAssemblyMethod.py
dnaweaver/DnaAssemblyMethod/GoldenGateAssemblyMethod.py
dnaweaver/DnaAssemblyMethod/OverlapingAssemblyMethod.py
dnaweaver-0.3.10.dist-info/licenses/LICENSE
dnaweaver-0.3.10.dist-info/METADATA
dnaweaver-0.3.10.dist-info/WHEEL
dnaweaver-0.3.10.dist-info/top_level.txt
dnaweaver-0.3.10.dist-info/RECORD
