Metadata-Version: 2.4
Name: dnaweaver
Version: 0.3.10
Summary: Make ordering and assembly plans for DNA sequences
Author: Zulko
License-Expression: MIT
Project-URL: Homepage, https://github.com/Edinburgh-Genome-Foundry/dnaweaver
Keywords: DNA,optimization,assembly,ordering,synthetic,biology
License-File: LICENSE
Requires-Dist: numpy
Requires-Dist: Biopython
Requires-Dist: proglog
Requires-Dist: networkx
Requires-Dist: flametree
Requires-Dist: dna_features_viewer
Requires-Dist: weasyprint
Requires-Dist: pandas
Requires-Dist: jinja2
Dynamic: license-file
